env_patch/__init__.py
env_patch/cli.py
env_patch-1.1.0.dist-info/METADATA
env_patch-1.1.0.dist-info/WHEEL
env_patch-1.1.0.dist-info/entry_points.txt
env_patch-1.1.0.dist-info/licenses/LICENSE
env_patch-1.1.0.dist-info/RECORD
