Metadata-Version: 2.4
Name: env-patch
Version: 1.1.0
Summary: Environment file generator with template + override support. Born from MochatAI team's production experience.
Project-URL: Homepage, https://github.com/upbrosai/env-patch
Project-URL: Repository, https://github.com/upbrosai/env-patch
Project-URL: Issues, https://github.com/upbrosai/env-patch/issues
Project-URL: Changelog, https://github.com/upbrosai/env-patch/blob/main/CHANGELOG.md
Author-email: MochatAI Team <dev@mochatai.com>
License: MIT
License-File: LICENSE
Keywords: cli,configuration,devops,dotenv,env,environment
Classifier: Development Status :: 5 - Production/Stable
Classifier: Environment :: Console
Classifier: Intended Audience :: Developers
Classifier: License :: OSI Approved :: MIT License
Classifier: Operating System :: OS Independent
Classifier: Programming Language :: Python :: 3
Classifier: Programming Language :: Python :: 3.8
Classifier: Programming Language :: Python :: 3.9
Classifier: Programming Language :: Python :: 3.10
Classifier: Programming Language :: Python :: 3.11
Classifier: Programming Language :: Python :: 3.12
Classifier: Programming Language :: Python :: 3.13
Classifier: Topic :: Software Development :: Build Tools
Classifier: Topic :: System :: Systems Administration
Classifier: Topic :: Utilities
Requires-Python: >=3.8
